sqlalchemy_database/__init__.py
sqlalchemy_database/_abc_async_database.py
sqlalchemy_database/_abc_async_database.pyi
sqlalchemy_database/database.py
sqlalchemy_database/utils.py
sqlalchemy_database-0.1.1.dist-info/WHEEL
sqlalchemy_database-0.1.1.dist-info/METADATA
sqlalchemy_database-0.1.1.dist-info/RECORD
