Metadata-Version: 2.1
Name: sqlalchemy_database
Version: 0.1.1
Summary: SQLAlchemy-Database provides shortcut functions to common database operations for SQLAlchemy ORM.
Keywords: SQLAlchemy-Database,SQLAlchemy,Database,AsyncDatabase,FastAPI-Amis-Admin
Author-email: Atomi <1456417373@qq.com>
Maintainer-email: Atomi <1456417373@qq.com>
Requires-Python: >=3.7
Classifier: Framework :: FastAPI
Classifier: Environment :: Web Environment
Classifier: Topic :: System :: Systems Administration
Classifier: License :: OSI Approved :: Apache Software License
Classifier: Operating System :: OS Independent
Classifier: Programming Language :: Python :: 3
Classifier: Programming Language :: Python :: 3.6
Classifier: Programming Language :: Python :: 3.7
Classifier: Programming Language :: Python :: 3.8
Classifier: Programming Language :: Python :: 3.9
Classifier: Programming Language :: Python :: 3.10
Classifier: Programming Language :: Python :: 3.11
Requires-Dist: sqlalchemy
Requires-Dist: mkdocs-material>=8.3.8 ; extra == "docs"
Requires-Dist: mkdocstrings[python]>=0.19.0 ; extra == "docs"
Requires-Dist: pytest >=6.2.4,<7.0.0 ; extra == "test"
Requires-Dist: aiosqlite ; extra == "test"
Requires-Dist: pytest-cov ; extra == "test"
Requires-Dist: pytest-asyncio>=0.17 ; extra == "test"
Requires-Dist: httpx ; extra == "test"
Requires-Dist: sqlmodel ; extra == "test"
Requires-Dist: fastapi ; extra == "test"
Project-URL: FastAPI-Amis-Admin, https://github.com/amisadmin/fastapi_amis_admin
Project-URL: Source, https://github.com/amisadmin/sqlalchemy_database
Provides-Extra: docs
Provides-Extra: test
